aws_allowlister/__init__.py
aws_allowlister/bin/__init__.py
aws_allowlister/bin/cli.py
aws_allowlister/bin/version.py
aws_allowlister/command/__init__.py
aws_allowlister/command/generate.py
aws_allowlister/data/compliance.db
aws_allowlister/data/hipaa-eligible-services-reference.html
aws_allowlister/data/iso-certified.html
aws_allowlister/data/overrides.yml
aws_allowlister/data/services-in-scope.html
aws_allowlister/database/__init__.py
aws_allowlister/database/build.py
aws_allowlister/database/compliance_data.py
aws_allowlister/database/database.py
aws_allowlister/database/raw_scraping_data.py
aws_allowlister/database/transformed_scraping_data.py
aws_allowlister/scrapers/__init__.py
aws_allowlister/scrapers/aws_docs.py
aws_allowlister/scrapers/common.py
aws_allowlister/scrapers/overrides.py
aws_allowlister/scrapers/tables/__init__.py
aws_allowlister/scrapers/tables/dodccsrg.py
aws_allowlister/scrapers/tables/fedramp.py
aws_allowlister/scrapers/tables/hipaa.py
aws_allowlister/scrapers/tables/hitrust.py
aws_allowlister/scrapers/tables/iso.py
aws_allowlister/scrapers/tables/standard.py
aws_allowlister/shared/__init__.py
aws_allowlister/shared/utils.py
aws_allowlister-0.2.15.dist-info/LICENSE
aws_allowlister-0.2.15.dist-info/METADATA
aws_allowlister-0.2.15.dist-info/WHEEL
aws_allowlister-0.2.15.dist-info/entry_points.txt
aws_allowlister-0.2.15.dist-info/top_level.txt
aws_allowlister-0.2.15.dist-info/zip-safe
aws_allowlister-0.2.15.dist-info/RECORD
