Metadata-Version: 2.1
Name: aws-allowlister
Version: 0.2.15
Summary: Generate AWS AllowList SCPs
Home-page: https://github.com/salesforce/aws-allowlister
Author: Kinnaird McQuade
Author-email: kinnairdm@gmail.com
Keywords: aws iam roles policy policies privileges security
Classifier: Programming Language :: Python :: 3
Classifier: License :: OSI Approved :: MIT License
Classifier: Operating System :: OS Independent
Requires-Python: >=3.7
License-File: LICENSE
Requires-Dist: beautifulsoup4
Requires-Dist: click
Requires-Dist: requests
Requires-Dist: policy-sentry
Requires-Dist: SQLAlchemy
Requires-Dist: tabulate
Requires-Dist: click-option-group
